LICENSE
MANIFEST.in
README
setup.py
docs/Makefile
docs/api.rst
docs/conf.py
docs/conn.rst
docs/history.rst
docs/index.rst
docs/keys.rst
docs/overview.rst
healthvaultlib/__init__.py
healthvaultlib/datatypes.py
healthvaultlib/exceptions.py
healthvaultlib/exceptions_flymake.py
healthvaultlib/healthvault.py
healthvaultlib/hvcrypto.py
healthvaultlib/makekey.py
healthvaultlib/status_codes.py
healthvaultlib/targets.py
healthvaultlib/xmlutils.py
python_healthvault.egg-info/PKG-INFO
python_healthvault.egg-info/SOURCES.txt
python_healthvault.egg-info/dependency_links.txt
python_healthvault.egg-info/requires.txt
python_healthvault.egg-info/top_level.txt