Metadata-Version: 1.1
Name: python-healthvault
Version: 0.1.5
Summary: Python library to access Microsoft Healthvault
Home-page: https://github.com/orcasgit/python-healthvault
Author: Dan Poirier and Caktus Group
Author-email: dpoirier@caktusgroup.com
License: Apache 2.0
Platform: UNKNOWN
Classifier: Development Status :: 4 - Beta
Classifier: Intended Audience :: Developers
Classifier: Programming Language :: Python
Classifier: License :: OSI Approved :: MIT License
Classifier: Programming Language :: Python :: 2.7
Classifier: Topic :: Software Development :: Libraries :: Python Modules
